jpcore/__init__.py
jpcore/compat.py
jpcore/component.py
jpcore/demoapp.py
jpcore/demostarter.py
jpcore/download.py
jpcore/example.py
jpcore/jpconfig.py
jpcore/justpy_app.py
jpcore/justpy_config.py
jpcore/tailwind.py
jpcore/template.py
jpcore/tutorial.py
jpcore/utilities.py
jpcore/webpage.py
justpy/__init__.py
justpy/htmlcomponents.py
justpy/justpy.py
justpy/templates/__init__.py
justpy/templates/favicon.html
justpy/templates/main.html
justpy/templates/optional_packages.html
justpy/templates/quasar.html
justpy/templates/svelte.html
justpy/templates/tailwind.html
justpy/templates/tailwindui.html
justpy/templates/css/form.css
justpy/templates/css/highcharts_jp.css
justpy/templates/css/pygments.css
justpy/templates/highcharts/avocado.js
justpy/templates/highcharts/dark-blue.js
justpy/templates/highcharts/dark-green.js
justpy/templates/highcharts/dark-unica.js
justpy/templates/highcharts/gray.js
justpy/templates/highcharts/grid-light.js
justpy/templates/highcharts/grid.js
justpy/templates/highcharts/high-contrast-dark.js
justpy/templates/highcharts/high-contrast-light.js
justpy/templates/highcharts/sand-signika.js
justpy/templates/highcharts/skies.js
justpy/templates/highcharts/slick.js
justpy/templates/highcharts/sunset.js
justpy/templates/js/event_handler.js
justpy/templates/js/justpy_core.js
justpy/templates/js/svelte/bundle.iife.js
justpy/templates/js/svelte/bundle.iife.js.map
justpy/templates/js/svelte/component_generator.js
justpy/templates/js/svelte/style.css
justpy/templates/js/vue/aggrid.js
justpy/templates/js/vue/altairjp.js
justpy/templates/js/vue/bokehjp.js
justpy/templates/js/vue/chartjp.js
justpy/templates/js/vue/component_generator.js
justpy/templates/js/vue/deckgl.js
justpy/templates/js/vue/editorjp.js
justpy/templates/js/vue/html_component.js
justpy/templates/js/vue/iframejp.js
justpy/templates/js/vue/katexjp.js
justpy/templates/js/vue/plotlyjp.js
justpy/templates/js/vue/quasar_component.js
justpy/templates/local/ag-grid-community.js
justpy_svelte-0.11.3.dist-info/METADATA
justpy_svelte-0.11.3.dist-info/WHEEL
justpy_svelte-0.11.3.dist-info/licenses/LICENSE
justpy_svelte-0.11.3.dist-info/RECORD
