Metadata-Version: 2.1
Name: justpy-svelte
Version: 0.11.3
Project-URL: Home, https://webworks.monallabs.in/justpy-svelte
Project-URL: Documentation, https://monallabs-org.github.io/justpy-svelte/
Project-URL: Source, https://github.com/Monallabs-org/justpy-svelte
Maintainer-email: Kabira K <kabira@monallabs.in>
License:                                  Apache License
License-File: LICENSE
Classifier: Development Status :: 4 - Beta
Classifier: Environment :: Web Environment
Classifier: Intended Audience :: Developers
Classifier: Intended Audience :: Education
Classifier: Intended Audience :: Science/Research
Classifier: License :: OSI Approved :: Apache Software License
Classifier: Operating System :: OS Independent
Classifier: Programming Language :: Python :: 3 :: Only
Classifier: Programming Language :: Python :: 3.7
Classifier: Programming Language :: Python :: 3.8
Classifier: Programming Language :: Python :: 3.9
Classifier: Programming Language :: Python :: 3.10
Classifier: Programming Language :: Python :: 3.11
Classifier: Topic :: Software Development :: User Interfaces
Requires-Python: >=3.7
Requires-Dist: addict-tracking-changes
Requires-Dist: aiofiles
Requires-Dist: hjson>=3.1.0
Requires-Dist: httpx>=0.23.0
Requires-Dist: itsdangerous>=2.1.2
Requires-Dist: jinja2>=3.1.2
Requires-Dist: psutil>=5.9.2
Requires-Dist: py-tailwind-utils
Requires-Dist: starlette>=0.20.4
Requires-Dist: twine
Requires-Dist: uvicorn>=0.18.3
Requires-Dist: websockets
Requires-Dist: wheel
